kube_secure/__init__.py
kube_secure/async_scanner.py
kube_secure/check_metadata.py
kube_secure/cli.py
kube_secure/connection.py
kube_secure/custom_rules_engine.py
kube_secure/logger.py
kube_secure/scanner.py
kube_secure/session.py
kube_sec-1.1.0.dist-info/METADATA
kube_sec-1.1.0.dist-info/WHEEL
kube_sec-1.1.0.dist-info/entry_points.txt
kube_sec-1.1.0.dist-info/top_level.txt
kube_sec-1.1.0.dist-info/RECORD
